pyavl_wrapper-1.8.1.dist-info/LICENSE.txt
pyavl_wrapper-1.8.1.dist-info/RECORD
pyavl_wrapper-1.8.1.dist-info/METADATA
pyavl_wrapper-1.8.1.dist-info/WHEEL
pyavl_wrapper.libs/libopenblasp-r0-23e5df77.3.21.dev.so
pyavl_wrapper.libs/libquadmath-96973f99.so.0.0.0
pyavl_wrapper.libs/libgfortran-040039e1.so.5.0.0
pyavl/om_wrapper.py
pyavl/pyAVL.py
pyavl/__init__.py
pyavl/MExt.py
pyavl/libavl.cpython-311-x86_64-linux-gnu.so
