Metadata-Version: 2.1
Name: pyavl-wrapper
Version: 1.8.1
Summary: A direct Python interface for Mark Drela and Harold Youngren's famous AVL code.
License: 
Project-URL: homepage, https://github.com/joanibal/pyavl
Project-URL: source, https://github.com/joanibal/pyavl
Project-URL: tracker, https://github.com/joanibal/pyavl/issues
Requires-Dist: numpy>=1.19
